lempdf/__init__.py
lempdf/pdf2image.py
lempdf/pdf2text.py
macpdf/__init__.py
macpdf/pdf2image.py
macpdf/pdf2text.py
macpdf-1.1.dist-info/LICENSE
macpdf-1.1.dist-info/METADATA
macpdf-1.1.dist-info/WHEEL
macpdf-1.1.dist-info/top_level.txt
macpdf-1.1.dist-info/RECORD
