Metadata-Version: 2.1
Name: macpdf
Version: 1.1
Summary: This is the latest package for translating pdf to other data format types.
Home-page: UNKNOWN
License: LICENSE
Platform: UNKNOWN
License-File: LICENSE
